fredlibs.py
fredlibs/__init__.py
fredlibs/version.py
fredlibs/aws/__init__.py
fredlibs/aws/ec2.py
fredlibs/display/__init__.py
fredlibs/utils/__init__.py
fredlibs-0.1.4.dist-info/DESCRIPTION.rst
fredlibs-0.1.4.dist-info/METADATA
fredlibs-0.1.4.dist-info/RECORD
fredlibs-0.1.4.dist-info/WHEEL
fredlibs-0.1.4.dist-info/metadata.json
fredlibs-0.1.4.dist-info/top_level.txt
