Metadata-Version: 2.0
Name: fredlibs
Version: 0.1.4
Summary: fredlibs package
Home-page: https://github.com/azafred/fredlibs
Author: Fred Vassard
Author-email: azafred@gmail.com
License: Copyright (c) 2012, Fred Vassard
Requires-Dist: nose
Requires-Dist: sphinx
Requires-Dist: recommonmark
Requires-Dist: boto
Requires-Dist: boto3
Requires-Dist: prettytable
